alidock/__init__.py
alidock/argumentparser.py
alidock/log.py
alidock/util.py
alidock/helpers/__init__.py
alidock/helpers/init.sh.j2
alidock-1.6.0.dist-info/LICENSE
alidock-1.6.0.dist-info/METADATA
alidock-1.6.0.dist-info/WHEEL
alidock-1.6.0.dist-info/entry_points.txt
alidock-1.6.0.dist-info/top_level.txt
alidock-1.6.0.dist-info/RECORD
