Metadata-Version: 2.1
Name: alidock
Version: 1.6.0
Summary: Run your ALICE environment from a container easily
Home-page: https://github.com/alidock/alidock
Author: Dario Berzano
Author-email: dario.berzano@cern.ch
License: GPL
Keywords: HEP computing container docker
Platform: UNKNOWN
Classifier: Development Status :: 5 - Production/Stable
Classifier: Intended Audience :: Education
Classifier: Intended Audience :: Developers
Classifier: Topic :: Scientific/Engineering :: Physics
Classifier: License :: OSI Approved :: GNU General Public License v3 (GPLv3)
Classifier: Programming Language :: Python :: 2.7
Classifier: Programming Language :: Python :: 3.7
Requires-Python: >=2.7
Requires-Dist: requests
Requires-Dist: PyYaml
Requires-Dist: docker
Requires-Dist: Jinja2
Requires-Dist: colorama
Requires-Dist: pathlib
Provides-Extra: devel
Requires-Dist: pylint (<=2.3.1) ; extra == 'devel'
Requires-Dist: twine (>=1.11.0) ; extra == 'devel'
Requires-Dist: setuptools (>=38.6.0) ; extra == 'devel'
Requires-Dist: wheel (>=0.31.0) ; extra == 'devel'
